skbel/__init__.py
skbel/algorithms/.DS_Store
skbel/algorithms/__init__.py
skbel/algorithms/extmath.py
skbel/algorithms/statistics.py
skbel/bnn/__init__.py
skbel/bnn/models.py
skbel/goggles/.DS_Store
skbel/goggles/__init__.py
skbel/goggles/visualization.py
skbel/learning/.DS_Store
skbel/learning/__init__.py
skbel/learning/bel.py
skbel/nn_utilities/__init__.py
skbel/nn_utilities/functions.py
skbel/preprocessing/.DS_Store
skbel/preprocessing/__init__.py
skbel/preprocessing/composite.py
skbel/preprocessing/dct.py
skbel/preprocessing/kernel.py
skbel/probabilities/__init__.py
skbel/probabilities/functions.py
skbel/spatial/__init__.py
skbel/spatial/spatial.py
skbel/testing/.DS_Store
skbel/testing/X_test.npy
skbel/testing/X_train.npy
skbel/testing/__init__.py
skbel/testing/ref_covariance.npy
skbel/testing/ref_mean.npy
skbel/testing/test_basic.py
skbel/testing/x_star_tm.npy
skbel/testing/y_samples_kde.npy
skbel/testing/y_train.npy
skbel/tmaps/__init__.py
skbel/tmaps/transport_map.py
skbel/utils/__init__.py
skbel/utils/utils.py
skbel-2.1.14.dist-info/LICENSE
skbel-2.1.14.dist-info/METADATA
skbel-2.1.14.dist-info/WHEEL
skbel-2.1.14.dist-info/top_level.txt
skbel-2.1.14.dist-info/RECORD
