Metadata-Version: 2.1
Name: skbel
Version: 2.1.14
Summary: A set of Python modules to implement the Bayesian Evidential Learning (BEL) framework
Home-page: https://github.com/robinthibaut/skbel
Author: Robin Thibaut
Author-email: robin.thibaut@UGent.be
License: BSD-3
Classifier: Intended Audience :: Science/Research
Classifier: License :: OSI Approved
Classifier: Programming Language :: Python
Classifier: Topic :: Scientific/Engineering
Classifier: Operating System :: Microsoft :: Windows
Classifier: Operating System :: Unix
Classifier: Operating System :: MacOS
Classifier: Programming Language :: Python :: 3.7
Classifier: Programming Language :: Python :: 3.8
Classifier: Programming Language :: Python :: 3.9
Classifier: Programming Language :: Python :: 3.10
Requires-Python: >=3.7
License-File: LICENSE
Requires-Dist: numpy
Requires-Dist: pandas
Requires-Dist: scipy
Requires-Dist: matplotlib
Requires-Dist: scikit-learn
Requires-Dist: scikit-image
Requires-Dist: joblib
Requires-Dist: pytest
